FollowWeb_Visualizor/__init__.py
FollowWeb_Visualizor/__main__.py
FollowWeb_Visualizor/main.py
FollowWeb_Visualizor/analysis/__init__.py
FollowWeb_Visualizor/analysis/centrality.py
FollowWeb_Visualizor/analysis/fame.py
FollowWeb_Visualizor/analysis/network.py
FollowWeb_Visualizor/analysis/paths.py
FollowWeb_Visualizor/core/__init__.py
FollowWeb_Visualizor/core/config.py
FollowWeb_Visualizor/core/exceptions.py
FollowWeb_Visualizor/core/types.py
FollowWeb_Visualizor/data/__init__.py
FollowWeb_Visualizor/data/cache.py
FollowWeb_Visualizor/data/loaders.py
FollowWeb_Visualizor/data/processors.py
FollowWeb_Visualizor/output/__init__.py
FollowWeb_Visualizor/output/formatters.py
FollowWeb_Visualizor/output/logging.py
FollowWeb_Visualizor/output/managers.py
FollowWeb_Visualizor/utils/__init__.py
FollowWeb_Visualizor/utils/files.py
FollowWeb_Visualizor/utils/math.py
FollowWeb_Visualizor/utils/parallel.py
FollowWeb_Visualizor/utils/progress.py
FollowWeb_Visualizor/utils/validation.py
FollowWeb_Visualizor/visualization/__init__.py
FollowWeb_Visualizor/visualization/colors.py
FollowWeb_Visualizor/visualization/legends.py
FollowWeb_Visualizor/visualization/metrics.py
FollowWeb_Visualizor/visualization/renderers.py
followweb_visualizor-1.0.1.dist-info/licenses/LICENSE
followweb_visualizor-1.0.1.dist-info/METADATA
followweb_visualizor-1.0.1.dist-info/WHEEL
followweb_visualizor-1.0.1.dist-info/entry_points.txt
followweb_visualizor-1.0.1.dist-info/top_level.txt
followweb_visualizor-1.0.1.dist-info/RECORD
