Metadata-Version: 2.4
Name: followweb-visualizor
Version: 1.0.1
Summary: Social network analysis and visualization tool for Instagram follower/following relationships with community detection and influence metrics
Author-email: FollowWeb Development Team <followweb.dev@example.com>
Maintainer-email: FollowWeb Development Team <followweb.dev@example.com>
License-Expression: MIT
Project-URL: Homepage, https://github.com/followweb/followweb-visualizor
Project-URL: Documentation, https://followweb-visualizor.readthedocs.io/
Project-URL: Repository, https://github.com/followweb/followweb-visualizor.git
Project-URL: Bug Tracker, https://github.com/followweb/followweb-visualizor/issues
Project-URL: Changelog, https://github.com/followweb/followweb-visualizor/blob/main/docs/CHANGELOG.md
Project-URL: Contributors, https://github.com/followweb/followweb-visualizor/blob/main/docs/attribution/CONTRIBUTORS.md
Project-URL: Dependencies Attribution, https://github.com/followweb/followweb-visualizor/blob/main/docs/attribution/DEPENDENCIES_ATTRIBUTION.md
Project-URL: License Notices, https://github.com/followweb/followweb-visualizor/blob/main/docs/attribution/LICENSE_NOTICES.md
Keywords: social network analysis,graph theory,network visualization,community detection,centrality analysis,instagram analysis,follower analysis,network metrics,social media analytics,graph algorithms,network science,social graphs
Classifier: Development Status :: 4 - Beta
Classifier: Intended Audience :: Developers
Classifier: Intended Audience :: Science/Research
Classifier: Intended Audience :: Education
Classifier: Topic :: Scientific/Engineering :: Information Analysis
Classifier: Topic :: Scientific/Engineering :: Visualization
Classifier: Topic :: Software Development :: Libraries :: Python Modules
Classifier: Topic :: Sociology
Classifier: Programming Language :: Python :: 3
Classifier: Programming Language :: Python :: 3.9
Classifier: Programming Language :: Python :: 3.10
Classifier: Programming Language :: Python :: 3.11
Classifier: Programming Language :: Python :: 3.12
Classifier: Operating System :: OS Independent
Requires-Python: >=3.9
License-File: LICENSE
Requires-Dist: networkx>=2.8.0
Requires-Dist: pandas>=1.5.0
Requires-Dist: matplotlib>=3.5.0
Requires-Dist: pyvis>=0.3.0
Requires-Dist: scipy>=1.9.0
Requires-Dist: nx-parallel>=0.3.0; python_version >= "3.11"
Provides-Extra: dev
Requires-Dist: pytest>=7.0.0; extra == "dev"
Requires-Dist: pytest-cov>=4.0.0; extra == "dev"
Requires-Dist: pytest-xdist>=3.0.0; extra == "dev"
Requires-Dist: pytest-timeout>=2.1.0; extra == "dev"
Requires-Dist: pytest-mock>=3.10.0; extra == "dev"
Requires-Dist: pytest-benchmark>=4.0.0; extra == "dev"
Requires-Dist: ruff>=0.1.0; extra == "dev"
Requires-Dist: mypy>=1.0.0; extra == "dev"
Requires-Dist: faker>=18.0.0; extra == "dev"
Requires-Dist: factory-boy>=3.2.0; extra == "dev"
Requires-Dist: pytest-doctestplus>=0.12.0; extra == "dev"
Requires-Dist: numpy>=1.21.0; extra == "dev"
Provides-Extra: test
Requires-Dist: pytest>=7.0.0; extra == "test"
Requires-Dist: pytest-cov>=4.0.0; extra == "test"
Requires-Dist: pytest-xdist>=3.0.0; extra == "test"
Requires-Dist: pytest-timeout>=2.1.0; extra == "test"
Requires-Dist: pytest-mock>=3.10.0; extra == "test"
Requires-Dist: pytest-benchmark>=4.0.0; extra == "test"
Requires-Dist: faker>=18.0.0; extra == "test"
Requires-Dist: factory-boy>=3.2.0; extra == "test"
Requires-Dist: pytest-doctestplus>=0.12.0; extra == "test"
Requires-Dist: numpy>=1.21.0; extra == "test"
Provides-Extra: docs
Requires-Dist: sphinx>=5.0.0; extra == "docs"
Requires-Dist: sphinx-rtd-theme>=1.0.0; extra == "docs"
Requires-Dist: myst-parser>=0.18.0; extra == "docs"
Dynamic: license-file
